{
  "lease_id": "lease-s1-budget-profile-agent-1-20260717",
  "stage_id": "s1-budget-profile",
  "agent_id": "agent-1",
  "issuer": "agent-0",
  "issued_at": "2026-07-17T11:33:50Z",
  "expires_at": "2026-07-17T17:33:50Z",
  "base_sha": "4cc95d80d23e36ffdb20250f6203510299de8faf",
  "public_authority_sha": "4cc95d80d23e36ffdb20250f6203510299de8faf",
  "branch": "codex/bridge-a1-s1-budget-profile",
  "worktree": "ephemeral-public-worktree:s1-budget-profile",
  "write_set": [
    "src/research_bridge/admission.py",
    "src/research_bridge/l0.py",
    "tests/test_stage1_admission.py",
    "tests/test_stage1_assurance.py",
    "tests/test_stage1_authority_policy.py",
    "tests/test_stage1_l0.py"
  ],
  "delegation_allowed": false,
  "state": "active"
}
